{
    "location": "Household B",
    "monthly_consumption_kwh": [
        {
            "month": "2023-01",
            "total_consumption_kwh": 320,
            "appliances": {
                "HVAC": 150,
                "Refrigerator": 50,
                "Washing Machine": 30,
                "Lighting": 60,
                "Electronics": 30
            }
        },
        {
            "month": "2023-02",
            "total_consumption_kwh": 290,
            "appliances": {
                "HVAC": 140,
                "Refrigerator": 48,
                "Washing Machine": 25,
                "Lighting": 50,
                "Electronics": 27
            }
        },
        {
            "month": "2023-03",
            "total_consumption_kwh": 310,
            "appliances": {
                "HVAC": 160,
                "Refrigerator": 49,
                "Washing Machine": 28,
                "Lighting": 52,
                "Electronics": 21
            }
        },
        {
            "month": "2023-04",
            "total_consumption_kwh": 400,
            "appliances": {
                "HVAC": 220,
                "Refrigerator": 52,
                "Washing Machine": 35,
                "Lighting": 60,
                "Electronics": 33
            }
        },
        {
            "month": "2023-05",
            "total_consumption_kwh": 350,
            "appliances": {
                "HVAC": 200,
                "Refrigerator": 53,
                "Washing Machine": 30,
                "Lighting": 45,
                "Electronics": 22
            }
        },
        {
            "month": "2023-06",
            "total_consumption_kwh": 370,
            "appliances": {
                "HVAC": 210,
                "Refrigerator": 54,
                "Washing Machine": 31,
                "Lighting": 50,
                "Electronics": 25
            }
        },
        {
            "month": "2023-07",
            "total_consumption_kwh": 410,
            "appliances": {
                "HVAC": 250,
                "Refrigerator": 56,
                "Washing Machine": 35,
                "Lighting": 45,
                "Electronics": 24
            }
        },
        {
            "month": "2023-08",
            "total_consumption_kwh": 390,
            "appliances": {
                "HVAC": 240,
                "Refrigerator": 55,
                "Washing Machine": 33,
                "Lighting": 40,
                "Electronics": 22
            }
        },
        {
            "month": "2023-09",
            "total_consumption_kwh": 360,
            "appliances": {
                "HVAC": 200,
                "Refrigerator": 52,
                "Washing Machine": 29,
                "Lighting": 50,
                "Electronics": 29
            }
        },
        {
            "month": "2023-10",
            "total_consumption_kwh": 330,
            "appliances": {
                "HVAC": 180,
                "Refrigerator": 50,
                "Washing Machine": 28,
                "Lighting": 52,
                "Electronics": 20
            }
        },
        {
            "month": "2023-11",
            "total_consumption_kwh": 300,
            "appliances": {
                "HVAC": 160,
                "Refrigerator": 48,
                "Washing Machine": 27,
                "Lighting": 45,
                "Electronics": 20
            }
        },
        {
            "month": "2023-12",
            "total_consumption_kwh": 340,
            "appliances": {
                "HVAC": 190,
                "Refrigerator": 51,
                "Washing Machine": 30,
                "Lighting": 48,
                "Electronics": 21
            }
        }
    ]
}

